joplin_vieweb/__init__.py
joplin_vieweb/admin.py
joplin_vieweb/apps.py
joplin_vieweb/edit_session.py
joplin_vieweb/hyperlink_preview_cache.py
joplin_vieweb/joplin.py
joplin_vieweb/lasts_notes.py
joplin_vieweb/models.py
joplin_vieweb/tests.py
joplin_vieweb/urls.py
joplin_vieweb/utils.py
joplin_vieweb/views.py
joplin_vieweb/joplin_api/__init__.py
joplin_vieweb/joplin_api/core.py
joplin_vieweb/joplin_api/core_sync.py
joplin_vieweb/migrations/__init__.py
joplin_vieweb/static/joplinvieweb/css/autosuggest.css
joplin_vieweb/static/joplinvieweb/css/clearable_input.css
joplin_vieweb/static/joplinvieweb/css/codehilite.css
joplin_vieweb/static/joplinvieweb/css/easymde.min.css
joplin_vieweb/static/joplinvieweb/css/hyperlink_preview.css
joplin_vieweb/static/joplinvieweb/css/joplin.css
joplin_vieweb/static/joplinvieweb/css/jqtree.css
joplin_vieweb/static/joplinvieweb/css/jquery.modal.min.css
joplin_vieweb/static/joplinvieweb/css/number.css
joplin_vieweb/static/joplinvieweb/css/popup.css
joplin_vieweb/static/joplinvieweb/css/pymdown_tab.css
joplin_vieweb/static/joplinvieweb/css/style-icomoon.css
joplin_vieweb/static/joplinvieweb/css/fonts/icomoon.eot
joplin_vieweb/static/joplinvieweb/css/fonts/icomoon.svg
joplin_vieweb/static/joplinvieweb/css/fonts/icomoon.ttf
joplin_vieweb/static/joplinvieweb/css/fonts/icomoon.woff
joplin_vieweb/static/joplinvieweb/img/close.gif
joplin_vieweb/static/joplinvieweb/img/favicon.ico
joplin_vieweb/static/joplinvieweb/img/progress.gif
joplin_vieweb/static/joplinvieweb/js/NoteEditor.js
joplin_vieweb/static/joplinvieweb/js/NoteTags.js
joplin_vieweb/static/joplinvieweb/js/NoteView.js
joplin_vieweb/static/joplinvieweb/js/NotesList.js
joplin_vieweb/static/joplinvieweb/js/SideBar.js
joplin_vieweb/static/joplinvieweb/js/clearable_input.js
joplin_vieweb/static/joplinvieweb/js/draggabilly.pkgd.min.js
joplin_vieweb/static/joplinvieweb/js/easymde.min.js
joplin_vieweb/static/joplinvieweb/js/joplinvieweb.js
joplin_vieweb/static/joplinvieweb/js/jquery-3.6.0.min.js
django_joplin_vieweb-1.17.0.dist-info/LICENSE
django_joplin_vieweb-1.17.0.dist-info/METADATA
django_joplin_vieweb-1.17.0.dist-info/WHEEL
django_joplin_vieweb-1.17.0.dist-info/top_level.txt
django_joplin_vieweb-1.17.0.dist-info/RECORD
