Metadata-Version: 2.1
Name: django-joplin-vieweb
Version: 1.17.0
Summary: A Django app to view your Joplin notes online.
Home-page: https://github.com/gri38/django-joplin_vieweb
Author: gri38
Author-email: onzeweb@zaclys.net
License: UNKNOWN
Project-URL: Bug Tracker, https://github.com/gri38/django-joplin_vieweb/issues
Platform: UNKNOWN
Classifier: Framework :: Django
Classifier: Framework :: Django :: 3.2
Classifier: License :: OSI Approved :: MIT License
Classifier: Operating System :: OS Independent
Classifier: Programming Language :: Python
Classifier: Programming Language :: Python :: 3
Requires-Python: >=3.6
License-File: LICENSE
Requires-Dist: Django (>=3.2)
Requires-Dist: httpx (>=0.18.1)
Requires-Dist: Markdown (>=3.3.4)
Requires-Dist: Pygments (>=2.9.0)
Requires-Dist: beautifulsoup4 (>=4.9.3)
Requires-Dist: pymdown-extensions (>=8.2)
Requires-Dist: hyperlink-preview (>=1.0.3)
Requires-Dist: joppy (==0.0.5)
